{
  "version": "1.1.1",
  "windows": {
    "main": {
      "main": true,
      "url": "app://editor/index.html",
      "windowType": "dockable",
      "x": -8,
      "y": -8,
      "width": 1552,
      "height": 840,
      "layout": {
        "children": [
          {
            "children": [
              {
                "active": 0,
                "children": [
                  "hierarchy"
                ],
                "height": 251.10000610351562,
                "type": "panel",
                "width": 300.95001220703125
              },
              {
                "active": 0,
                "children": [
                  "assets",
                  "cloud-function"
                ],
                "height": 468.5,
                "type": "panel",
                "width": 300.95001220703125
              }
            ],
            "height": 722.6000366210938,
            "type": "dock-v",
            "width": 300.95001220703125
          },
          {
            "children": [
              {
                "children": [
                  {
                    "active": 0,
                    "children": [
                      "scene"
                    ],
                    "height": 448.0874938964844,
                    "type": "panel",
                    "width": 570.6124877929688
                  },
                  {
                    "active": 0,
                    "children": [
                      "node-library"
                    ],
                    "height": 448.0874938964844,
                    "type": "panel",
                    "width": 285.8125
                  }
                ],
                "height": 448.0874938964844,
                "type": "dock-h",
                "width": 859.4249877929688
              },
              {
                "active": 0,
                "children": [
                  "console",
                  "timeline",
                  "game-window"
                ],
                "height": 271.51251220703125,
                "type": "panel",
                "width": 859.4249877929688
              }
            ],
            "height": 722.6000366210938,
            "type": "dock-v",
            "width": 859.4249877929688
          },
          {
            "active": 0,
            "children": [
              "inspector",
              "cocos-services"
            ],
            "height": 722.6000366210938,
            "type": "panel",
            "width": 369.625
          }
        ],
        "type": "dock-h"
      },
      "panels": [
        "hierarchy",
        "assets",
        "cloud-function",
        "scene",
        "node-library",
        "console",
        "timeline",
        "game-window",
        "inspector",
        "cocos-services"
      ]
    }
  },
  "panels": {
    "builder": {
      "x": 508,
      "y": 28,
      "width": 516,
      "height": 740
    }
  },
  "panelLabelWidth": {
    "builder": null,
    "inspector": null
  }
}
